LICENSE.txt
MANIFEST.in
README.rst
setup.cfg
setup.py
SdCalculator.egg-info/PKG-INFO
SdCalculator.egg-info/SOURCES.txt
SdCalculator.egg-info/dependency_links.txt
SdCalculator.egg-info/top_level.txt
calculator/__init__.py
calculator/calculator.py